nonebot_plugin_RanFurryPic/__init__.py
nonebot_plugin_RanFurryPic/config.py
nonebot_plugin_RanFurryPic-1.1.9.dist-info/LICENSE
nonebot_plugin_RanFurryPic-1.1.9.dist-info/METADATA
nonebot_plugin_RanFurryPic-1.1.9.dist-info/WHEEL
nonebot_plugin_RanFurryPic-1.1.9.dist-info/top_level.txt
nonebot_plugin_RanFurryPic-1.1.9.dist-info/RECORD
