Metadata-Version: 2.1
Name: nonebot_plugin_RanFurryPic
Version: 1.1.9
Summary: 基于NoneBot2进行适配的兽云随机毛图插件
Author-email: Ekac <2396382559@qq.com>
License: MIT
Requires-Python: >=3.9
License-File: LICENSE
Requires-Dist: nonebot2
Requires-Dist: httpx
Requires-Dist: nonebot-plugin-send-anything-anywhere
